{
    "background": {
        "anchorX": 0,
        "anchorY": 0,
        "offsetX": 1,
        "offsetY": 8,
        "fit": "fill",
        "scaleX": 1,
        "scaleY": 1,
        "rotation": 0,
        "tint": "#ffffff",
        "alphaThreshold": 0
    },
    "backgroundColor": "#68643a",
    "drawings": [],
    "environment": {
        "darknessLevel": 0,
        "darknessLock": false,
        "globalLight": {
            "enabled": true,
            "alpha": 0.5,
            "bright": false,
            "color": null,
            "coloration": 1,
            "luminosity": 0,
            "saturation": 0,
            "contrast": 0,
            "shadows": 0,
            "darkness": {
                "min": 0,
                "max": 0.6
            }
        },
        "cycle": true,
        "base": {
            "hue": 0,
            "intensity": 0,
            "luminosity": 0,
            "saturation": 0,
            "shadows": 0
        },
        "dark": {
            "hue": 0.7138888888888889,
            "intensity": 0,
            "luminosity": -0.25,
            "saturation": 0,
            "shadows": 0
        }
    },
    "flags": {
        "ddb": {
            "bookCode": "hotb",
            "ddbId": 10048,
            "cobaltId": null,
            "parentId": 2567,
            "contentChunkId": "MapHobgoblinPatrol-map",
            "notes": [],
            "tokens": [
                {
                    "_id": "hx9bK6Yxgj8BDmbv",
                    "name": "Hobgoblin Warrior",
                    "width": 1,
                    "height": 1,
                    "x": 1000,
                    "y": 1300,
                    "disposition": -1,
                    "flags": {
                        "ddbActorFlags": {
                            "id": 5195079,
                            "entityTypeId": 779871897,
                            "creatureGroupId": null,
                            "creatureFlags": [],
                            "version": "999.0.0",
                            "isLegacy": false,
                            "sources": [
                                {
                                    "sourceId": 147,
                                    "pageNumber": 170,
                                    "sourceType": 1
                                }
                            ],
                            "compendiumId": "ddbHobWar5195079",
                            "sourceId": 147,
                            "sourceCategory": 24,
                            "flatAC": false,
                            "name": "Hobgoblin Warrior"
                        }
                    },
                    "actorLink": false,
                    "bar1": {
                        "attribute": "attributes.hp"
                    },
                    "elevation": 0,
                    "hidden": true,
                    "actorData": {
                        "_id": "hnFnuwPadWVIXPdt",
                        "system": {},
                        "flags": {}
                    },
                    "light": {
                        "negative": false,
                        "priority": 0,
                        "alpha": 0.5,
                        "angle": 360,
                        "bright": 0,
                        "color": null,
                        "coloration": 1,
                        "dim": 0,
                        "attenuation": 0.5,
                        "luminosity": 0.5,
                        "saturation": 0,
                        "contrast": 0,
                        "shadows": 0,
                        "animation": {
                            "type": null,
                            "speed": 5,
                            "intensity": 5,
                            "reverse": false
                        },
                        "darkness": {
                            "min": 0,
                            "max": 1
                        }
                    }
                },
                {
                    "_id": "zAQ5GW3W7r7pw46H",
                    "name": "Hobgoblin Warrior",
                    "width": 1,
                    "height": 1,
                    "x": 800,
                    "y": 1400,
                    "disposition": -1,
                    "flags": {
                        "ddbActorFlags": {
                            "id": 5195079,
                            "entityTypeId": 779871897,
                            "creatureGroupId": null,
                            "creatureFlags": [],
                            "version": "999.0.0",
                            "isLegacy": false,
                            "sources": [
                                {
                                    "sourceId": 147,
                                    "pageNumber": 170,
                                    "sourceType": 1
                                }
                            ],
                            "compendiumId": "ddbHobWar5195079",
                            "sourceId": 147,
                            "sourceCategory": 24,
                            "flatAC": false,
                            "name": "Hobgoblin Warrior"
                        }
                    },
                    "actorLink": false,
                    "bar1": {
                        "attribute": "attributes.hp"
                    },
                    "elevation": 0,
                    "hidden": true,
                    "actorData": {
                        "_id": "hnFnuwPadWVIXPdt",
                        "system": {},
                        "flags": {}
                    },
                    "light": {
                        "negative": false,
                        "priority": 0,
                        "alpha": 0.5,
                        "angle": 360,
                        "bright": 0,
                        "color": null,
                        "coloration": 1,
                        "dim": 0,
                        "attenuation": 0.5,
                        "luminosity": 0.5,
                        "saturation": 0,
                        "contrast": 0,
                        "shadows": 0,
                        "animation": {
                            "type": null,
                            "speed": 5,
                            "intensity": 5,
                            "reverse": false
                        },
                        "darkness": {
                            "min": 0,
                            "max": 1
                        }
                    }
                },
                {
                    "_id": "gbZiSMEUmbTIXHIq",
                    "name": "Hobgoblin Warrior",
                    "width": 1,
                    "height": 1,
                    "x": 800,
                    "y": 1600,
                    "disposition": -1,
                    "flags": {
                        "ddbActorFlags": {
                            "id": 5195079,
                            "entityTypeId": 779871897,
                            "creatureGroupId": null,
                            "creatureFlags": [],
                            "version": "999.0.0",
                            "isLegacy": false,
                            "sources": [
                                {
                                    "sourceId": 147,
                                    "pageNumber": 170,
                                    "sourceType": 1
                                }
                            ],
                            "compendiumId": "ddbHobWar5195079",
                            "sourceId": 147,
                            "sourceCategory": 24,
                            "flatAC": false,
                            "name": "Hobgoblin Warrior"
                        }
                    },
                    "actorLink": false,
                    "bar1": {
                        "attribute": "attributes.hp"
                    },
                    "elevation": 0,
                    "hidden": true,
                    "actorData": {
                        "_id": "hnFnuwPadWVIXPdt",
                        "system": {},
                        "flags": {}
                    },
                    "light": {
                        "negative": false,
                        "priority": 0,
                        "alpha": 0.5,
                        "angle": 360,
                        "bright": 0,
                        "color": null,
                        "coloration": 1,
                        "dim": 0,
                        "attenuation": 0.5,
                        "luminosity": 0.5,
                        "saturation": 0,
                        "contrast": 0,
                        "shadows": 0,
                        "animation": {
                            "type": null,
                            "speed": 5,
                            "intensity": 5,
                            "reverse": false
                        },
                        "darkness": {
                            "min": 0,
                            "max": 1
                        }
                    }
                }
            ],
            "originalLink": "ddb://image/hotb/map-3.12-hobgoblin-patrol.png",
            "foundryVersion": "13.348",
            "versions": {
                "ddbMetaData": {
                    "name": "Map: Hobgoblin Patrol",
                    "bookCode": "hotb",
                    "contentChunkId": "MapHobgoblinPatrol-map",
                    "lastUpdate": "1.1.16",
                    "notes": "1.1.16",
                    "tokens": "1.1.16",
                    "walls": "1.1.16",
                    "lights": "1.1.16",
                    "drawings": "1.1.16",
                    "regions": "1.1.16",
                    "foundry": "13.348"
                }
            }
        },
        "stairways": {},
        "perfect-vision": {},
        "dynamic-illumination": {},
        "ddbimporter": {
            "version": "999.0.0"
        }
    },
    "fog": {
        "colors": {
            "explored": null,
            "unexplored": null
        },
        "exploration": true,
        "overlay": null
    },
    "foregroundElevation": 20,
    "grid": {
        "type": 1,
        "size": 100,
        "sizeX": 100,
        "sizeY": 100,
        "distance": 5,
        "units": "ft",
        "style": "solidLines",
        "thickness": 1,
        "color": "#000000",
        "alpha": 0,
        "diagonals": 0
    },
    "height": 2210,
    "initial": {
        "x": null,
        "y": null,
        "scale": null
    },
    "lights": [],
    "name": "Map: Hobgoblin Patrol",
    "navName": "Map: Hobgoblin Patrol",
    "navOrder": 100001,
    "padding": 0.25,
    "regions": [],
    "tokenVision": true,
    "walls": [],
    "weather": "",
    "width": 1501
}