{
    "background": {
        "anchorX": 0,
        "anchorY": 0,
        "offsetX": 7,
        "offsetY": -17,
        "fit": "fill",
        "scaleX": 1,
        "scaleY": 1,
        "rotation": 0,
        "tint": "#ffffff",
        "alphaThreshold": 0
    },
    "backgroundColor": "#999999",
    "darkness": 0,
    "drawings": [],
    "flags": {
        "ddb": {
            "bookCode": "uhlh",
            "ddbId": 10003,
            "cobaltId": null,
            "parentId": 2115,
            "contentChunkId": "Map11WoodlandPool-player",
            "notes": [
                {
                    "label": "Pool Confrontation",
                    "flags": {
                        "ddb": {
                            "cobaltId": null,
                            "ddbId": 2,
                            "bookCode": "uhlh",
                            "slug": "uni-and-the-hunt-for-the-lost-horn#UniinDanger",
                            "linkName": "Uni in Danger",
                            "slugLink": "PoolConfrontation",
                            "duplicate": false,
                            "contentChunkId": null,
                            "img": false,
                            "note": false,
                            "parentId": 2115,
                            "labelName": "Pool Confrontation"
                        }
                    },
                    "texture": {
                        "src": "icons/svg/book.svg",
                        "anchorX": 0.5,
                        "anchorY": 0.5,
                        "offsetX": 0,
                        "offsetY": 0,
                        "fit": "contain",
                        "scaleX": 1,
                        "scaleY": 1,
                        "rotation": 0,
                        "tint": "#ffffff",
                        "alphaThreshold": 0
                    },
                    "positions": [
                        {
                            "x": 5000,
                            "y": 2100
                        }
                    ],
                    "iconSize": 40,
                    "textColor": "#ffffff",
                    "textAnchor": 1
                },
                {
                    "label": "Woodland Pool Features",
                    "flags": {
                        "ddb": {
                            "cobaltId": null,
                            "ddbId": 2,
                            "bookCode": "uhlh",
                            "slug": "uni-and-the-hunt-for-the-lost-horn#UniinDanger",
                            "linkName": "Uni in Danger",
                            "slugLink": "WoodlandPoolFeatures",
                            "duplicate": false,
                            "contentChunkId": null,
                            "img": false,
                            "note": false,
                            "parentId": 2115,
                            "labelName": "Woodland Pool Features"
                        }
                    },
                    "texture": {
                        "src": "icons/svg/book.svg",
                        "anchorX": 0.5,
                        "anchorY": 0.5,
                        "offsetX": 0,
                        "offsetY": 0,
                        "fit": "contain",
                        "scaleX": 1,
                        "scaleY": 1,
                        "rotation": 0,
                        "tint": "#ffffff",
                        "alphaThreshold": 0
                    },
                    "positions": [
                        {
                            "x": 3950,
                            "y": 1050
                        }
                    ],
                    "iconSize": 40,
                    "textColor": "#ffffff",
                    "textAnchor": 1
                },
                {
                    "label": "Uni in Danger",
                    "flags": {
                        "ddb": {
                            "cobaltId": null,
                            "ddbId": 2,
                            "bookCode": "uhlh",
                            "slug": "uni-and-the-hunt-for-the-lost-horn#UniinDanger",
                            "linkName": "Uni in Danger",
                            "slugLink": "UniinDanger",
                            "duplicate": false,
                            "contentChunkId": null,
                            "img": false,
                            "note": false,
                            "parentId": 2115
                        }
                    },
                    "texture": {
                        "src": "icons/svg/book.svg",
                        "anchorX": 0.5,
                        "anchorY": 0.5,
                        "offsetX": 0,
                        "offsetY": 0,
                        "fit": "contain",
                        "scaleX": 1,
                        "scaleY": 1,
                        "rotation": 0,
                        "tint": "#ffffff",
                        "alphaThreshold": 0
                    },
                    "positions": [
                        {
                            "x": 3100,
                            "y": 2100
                        }
                    ],
                    "iconSize": 40,
                    "textColor": "#ffffff",
                    "textAnchor": 1
                }
            ],
            "tokens": [
                {
                    "_id": "AaeofQYW90xwnZui",
                    "name": "Willowbrush",
                    "width": 0.5,
                    "height": 0.5,
                    "x": 3100,
                    "y": 2025,
                    "disposition": 1,
                    "flags": {
                        "ddbActorFlags": {
                            "id": 4775845,
                            "entityTypeId": 779871897,
                            "creatureGroupId": null,
                            "creatureFlags": [],
                            "version": "999.0.0",
                            "isLegacy": false,
                            "flatAC": false,
                            "name": "Sprite"
                        }
                    },
                    "actorLink": false,
                    "bar1": {
                        "attribute": "attributes.hp"
                    },
                    "elevation": 0,
                    "hidden": true,
                    "actorData": {
                        "_id": "AaeofQYW90xwnZui",
                        "name": "Willowbrush",
                        "system": {},
                        "flags": {}
                    },
                    "light": {
                        "negative": false,
                        "priority": 0,
                        "alpha": 0.5,
                        "angle": 360,
                        "bright": 0,
                        "color": null,
                        "coloration": 1,
                        "dim": 0,
                        "attenuation": 0.5,
                        "luminosity": 0.5,
                        "saturation": 0,
                        "contrast": 0,
                        "shadows": 0,
                        "animation": {
                            "type": null,
                            "speed": 5,
                            "intensity": 5,
                            "reverse": false
                        },
                        "darkness": {
                            "min": 0,
                            "max": 1
                        }
                    }
                },
                {
                    "_id": "gRWDG2wEQsIFJGaz",
                    "name": "Knock",
                    "width": 0.5,
                    "height": 0.5,
                    "x": 5200,
                    "y": 2800,
                    "disposition": 1,
                    "flags": {
                        "ddbActorFlags": {
                            "id": 4775845,
                            "entityTypeId": 779871897,
                            "creatureGroupId": null,
                            "creatureFlags": [],
                            "version": "999.0.0",
                            "isLegacy": false,
                            "flatAC": false,
                            "name": "Sprite"
                        }
                    },
                    "actorLink": false,
                    "bar1": {
                        "attribute": "attributes.hp"
                    },
                    "elevation": 0,
                    "hidden": true,
                    "actorData": {
                        "_id": "gRWDG2wEQsIFJGaz",
                        "name": "Knock",
                        "system": {},
                        "flags": {}
                    },
                    "light": {
                        "negative": false,
                        "priority": 0,
                        "alpha": 0.5,
                        "angle": 360,
                        "bright": 0,
                        "color": null,
                        "coloration": 1,
                        "dim": 0,
                        "attenuation": 0.5,
                        "luminosity": 0.5,
                        "saturation": 0,
                        "contrast": 0,
                        "shadows": 0,
                        "animation": {
                            "type": null,
                            "speed": 5,
                            "intensity": 5,
                            "reverse": false
                        },
                        "darkness": {
                            "min": 0,
                            "max": 1
                        }
                    }
                },
                {
                    "_id": "AOZ6QAbDGyhs7YTn",
                    "name": "Grump",
                    "width": 1,
                    "height": 1,
                    "x": 5900,
                    "y": 1100,
                    "disposition": -1,
                    "flags": {
                        "ddbActorFlags": {
                            "id": 4831002,
                            "entityTypeId": 779871897,
                            "creatureGroupId": null,
                            "creatureFlags": [],
                            "version": "999.0.0",
                            "isLegacy": false,
                            "flatAC": false,
                            "name": "Bugbear Warrior"
                        }
                    },
                    "actorLink": false,
                    "bar1": {
                        "attribute": "attributes.hp"
                    },
                    "elevation": 0,
                    "hidden": true,
                    "actorData": {
                        "_id": "AOZ6QAbDGyhs7YTn",
                        "name": "Grump",
                        "system": {},
                        "flags": {}
                    },
                    "light": {
                        "negative": false,
                        "priority": 0,
                        "alpha": 0.5,
                        "angle": 360,
                        "bright": 0,
                        "color": null,
                        "coloration": 1,
                        "dim": 0,
                        "attenuation": 0.5,
                        "luminosity": 0.5,
                        "saturation": 0,
                        "contrast": 0,
                        "shadows": 0,
                        "animation": {
                            "type": null,
                            "speed": 5,
                            "intensity": 5,
                            "reverse": false
                        },
                        "darkness": {
                            "min": 0,
                            "max": 1
                        }
                    }
                },
                {
                    "_id": "Wi19H2b132oxXj4b",
                    "name": "Bullywug Warrior",
                    "width": 1,
                    "height": 1,
                    "x": 5300,
                    "y": 1300,
                    "disposition": -1,
                    "flags": {
                        "ddbActorFlags": {
                            "id": 4831017,
                            "entityTypeId": 779871897,
                            "creatureGroupId": null,
                            "creatureFlags": [],
                            "version": "999.0.0",
                            "isLegacy": false,
                            "flatAC": false,
                            "name": "Bullywug Warrior"
                        }
                    },
                    "actorLink": false,
                    "bar1": {
                        "attribute": "attributes.hp"
                    },
                    "elevation": 0,
                    "hidden": true,
                    "actorData": {
                        "_id": "eE2ESlyjy6VTBlIX",
                        "system": {},
                        "flags": {}
                    },
                    "light": {
                        "negative": false,
                        "priority": 0,
                        "alpha": 0.5,
                        "angle": 360,
                        "bright": 0,
                        "color": null,
                        "coloration": 1,
                        "dim": 0,
                        "attenuation": 0.5,
                        "luminosity": 0.5,
                        "saturation": 0,
                        "contrast": 0,
                        "shadows": 0,
                        "animation": {
                            "type": null,
                            "speed": 5,
                            "intensity": 5,
                            "reverse": false
                        },
                        "darkness": {
                            "min": 0,
                            "max": 1
                        }
                    }
                },
                {
                    "_id": "Ts7eEMK5dog1BZT4",
                    "name": "Bullywug Warrior",
                    "width": 1,
                    "height": 1,
                    "x": 5000,
                    "y": 1700,
                    "disposition": -1,
                    "flags": {
                        "ddbActorFlags": {
                            "id": 4831017,
                            "entityTypeId": 779871897,
                            "creatureGroupId": null,
                            "creatureFlags": [],
                            "version": "999.0.0",
                            "isLegacy": false,
                            "flatAC": false,
                            "name": "Bullywug Warrior"
                        }
                    },
                    "actorLink": false,
                    "bar1": {
                        "attribute": "attributes.hp"
                    },
                    "elevation": 0,
                    "hidden": true,
                    "actorData": {
                        "_id": "eE2ESlyjy6VTBlIX",
                        "system": {},
                        "flags": {}
                    },
                    "light": {
                        "negative": false,
                        "priority": 0,
                        "alpha": 0.5,
                        "angle": 360,
                        "bright": 0,
                        "color": null,
                        "coloration": 1,
                        "dim": 0,
                        "attenuation": 0.5,
                        "luminosity": 0.5,
                        "saturation": 0,
                        "contrast": 0,
                        "shadows": 0,
                        "animation": {
                            "type": null,
                            "speed": 5,
                            "intensity": 5,
                            "reverse": false
                        },
                        "darkness": {
                            "min": 0,
                            "max": 1
                        }
                    }
                },
                {
                    "_id": "qHRvkkj6WFuPsSG0",
                    "name": "Bullywug Warrior",
                    "width": 1,
                    "height": 1,
                    "x": 4700,
                    "y": 1700,
                    "disposition": -1,
                    "flags": {
                        "ddbActorFlags": {
                            "id": 4831017,
                            "entityTypeId": 779871897,
                            "creatureGroupId": null,
                            "creatureFlags": [],
                            "version": "999.0.0",
                            "isLegacy": false,
                            "flatAC": false,
                            "name": "Bullywug Warrior"
                        }
                    },
                    "actorLink": false,
                    "bar1": {
                        "attribute": "attributes.hp"
                    },
                    "elevation": 0,
                    "hidden": true,
                    "actorData": {
                        "_id": "eE2ESlyjy6VTBlIX",
                        "system": {},
                        "flags": {}
                    },
                    "light": {
                        "negative": false,
                        "priority": 0,
                        "alpha": 0.5,
                        "angle": 360,
                        "bright": 0,
                        "color": null,
                        "coloration": 1,
                        "dim": 0,
                        "attenuation": 0.5,
                        "luminosity": 0.5,
                        "saturation": 0,
                        "contrast": 0,
                        "shadows": 0,
                        "animation": {
                            "type": null,
                            "speed": 5,
                            "intensity": 5,
                            "reverse": false
                        },
                        "darkness": {
                            "min": 0,
                            "max": 1
                        }
                    }
                },
                {
                    "_id": "FoxBog515Kje8Xkr",
                    "name": "Bullywug Warrior",
                    "width": 1,
                    "height": 1,
                    "x": 4700,
                    "y": 2000,
                    "disposition": -1,
                    "flags": {
                        "ddbActorFlags": {
                            "id": 4831017,
                            "entityTypeId": 779871897,
                            "creatureGroupId": null,
                            "creatureFlags": [],
                            "version": "999.0.0",
                            "isLegacy": false,
                            "flatAC": false,
                            "name": "Bullywug Warrior"
                        }
                    },
                    "actorLink": false,
                    "bar1": {
                        "attribute": "attributes.hp"
                    },
                    "elevation": 0,
                    "hidden": true,
                    "actorData": {
                        "_id": "eE2ESlyjy6VTBlIX",
                        "system": {},
                        "flags": {}
                    },
                    "light": {
                        "negative": false,
                        "priority": 0,
                        "alpha": 0.5,
                        "angle": 360,
                        "bright": 0,
                        "color": null,
                        "coloration": 1,
                        "dim": 0,
                        "attenuation": 0.5,
                        "luminosity": 0.5,
                        "saturation": 0,
                        "contrast": 0,
                        "shadows": 0,
                        "animation": {
                            "type": null,
                            "speed": 5,
                            "intensity": 5,
                            "reverse": false
                        },
                        "darkness": {
                            "min": 0,
                            "max": 1
                        }
                    }
                },
                {
                    "_id": "0slU5mIyfE5kd6ZL",
                    "name": "Bullywug Warrior",
                    "width": 1,
                    "height": 1,
                    "x": 5400,
                    "y": 2200,
                    "disposition": -1,
                    "flags": {
                        "ddbActorFlags": {
                            "id": 4831017,
                            "entityTypeId": 779871897,
                            "creatureGroupId": null,
                            "creatureFlags": [],
                            "version": "999.0.0",
                            "isLegacy": false,
                            "flatAC": false,
                            "name": "Bullywug Warrior"
                        }
                    },
                    "actorLink": false,
                    "bar1": {
                        "attribute": "attributes.hp"
                    },
                    "elevation": 0,
                    "hidden": true,
                    "actorData": {
                        "_id": "eE2ESlyjy6VTBlIX",
                        "system": {},
                        "flags": {}
                    },
                    "light": {
                        "negative": false,
                        "priority": 0,
                        "alpha": 0.5,
                        "angle": 360,
                        "bright": 0,
                        "color": null,
                        "coloration": 1,
                        "dim": 0,
                        "attenuation": 0.5,
                        "luminosity": 0.5,
                        "saturation": 0,
                        "contrast": 0,
                        "shadows": 0,
                        "animation": {
                            "type": null,
                            "speed": 5,
                            "intensity": 5,
                            "reverse": false
                        },
                        "darkness": {
                            "min": 0,
                            "max": 1
                        }
                    }
                },
                {
                    "_id": "yfkCQMjI47btR6Xh",
                    "name": "Bullywug Warrior",
                    "width": 1,
                    "height": 1,
                    "x": 4900,
                    "y": 2300,
                    "disposition": -1,
                    "flags": {
                        "ddbActorFlags": {
                            "id": 4831017,
                            "entityTypeId": 779871897,
                            "creatureGroupId": null,
                            "creatureFlags": [],
                            "version": "999.0.0",
                            "isLegacy": false,
                            "flatAC": false,
                            "name": "Bullywug Warrior"
                        }
                    },
                    "actorLink": false,
                    "bar1": {
                        "attribute": "attributes.hp"
                    },
                    "elevation": 0,
                    "hidden": true,
                    "actorData": {
                        "_id": "eE2ESlyjy6VTBlIX",
                        "system": {},
                        "flags": {}
                    },
                    "light": {
                        "negative": false,
                        "priority": 0,
                        "alpha": 0.5,
                        "angle": 360,
                        "bright": 0,
                        "color": null,
                        "coloration": 1,
                        "dim": 0,
                        "attenuation": 0.5,
                        "luminosity": 0.5,
                        "saturation": 0,
                        "contrast": 0,
                        "shadows": 0,
                        "animation": {
                            "type": null,
                            "speed": 5,
                            "intensity": 5,
                            "reverse": false
                        },
                        "darkness": {
                            "min": 0,
                            "max": 1
                        }
                    }
                },
                {
                    "_id": "xbaeGwz4cOTzsCK6",
                    "name": "Bullywug Warrior",
                    "width": 1,
                    "height": 1,
                    "x": 4600,
                    "y": 2100,
                    "disposition": -1,
                    "flags": {
                        "ddbActorFlags": {
                            "id": 4831017,
                            "entityTypeId": 779871897,
                            "creatureGroupId": null,
                            "creatureFlags": [],
                            "version": "999.0.0",
                            "isLegacy": false,
                            "flatAC": false,
                            "name": "Bullywug Warrior"
                        }
                    },
                    "actorLink": false,
                    "bar1": {
                        "attribute": "attributes.hp"
                    },
                    "elevation": 0,
                    "hidden": true,
                    "actorData": {
                        "_id": "eE2ESlyjy6VTBlIX",
                        "system": {},
                        "flags": {}
                    },
                    "light": {
                        "negative": false,
                        "priority": 0,
                        "alpha": 0.5,
                        "angle": 360,
                        "bright": 0,
                        "color": null,
                        "coloration": 1,
                        "dim": 0,
                        "attenuation": 0.5,
                        "luminosity": 0.5,
                        "saturation": 0,
                        "contrast": 0,
                        "shadows": 0,
                        "animation": {
                            "type": null,
                            "speed": 5,
                            "intensity": 5,
                            "reverse": false
                        },
                        "darkness": {
                            "min": 0,
                            "max": 1
                        }
                    }
                },
                {
                    "_id": "KtxItHCBDdUeLsgn",
                    "name": "Bullywug Warrior",
                    "width": 1,
                    "height": 1,
                    "x": 4300,
                    "y": 1900,
                    "disposition": -1,
                    "flags": {
                        "ddbActorFlags": {
                            "id": 4831017,
                            "entityTypeId": 779871897,
                            "creatureGroupId": null,
                            "creatureFlags": [],
                            "version": "999.0.0",
                            "isLegacy": false,
                            "flatAC": false,
                            "name": "Bullywug Warrior"
                        }
                    },
                    "actorLink": false,
                    "bar1": {
                        "attribute": "attributes.hp"
                    },
                    "elevation": 0,
                    "hidden": true,
                    "actorData": {
                        "_id": "eE2ESlyjy6VTBlIX",
                        "system": {},
                        "flags": {}
                    },
                    "light": {
                        "negative": false,
                        "priority": 0,
                        "alpha": 0.5,
                        "angle": 360,
                        "bright": 0,
                        "color": null,
                        "coloration": 1,
                        "dim": 0,
                        "attenuation": 0.5,
                        "luminosity": 0.5,
                        "saturation": 0,
                        "contrast": 0,
                        "shadows": 0,
                        "animation": {
                            "type": null,
                            "speed": 5,
                            "intensity": 5,
                            "reverse": false
                        },
                        "darkness": {
                            "min": 0,
                            "max": 1
                        }
                    }
                },
                {
                    "_id": "QkYDgDfYf93e8jEG",
                    "name": "Bullywug Warrior",
                    "width": 1,
                    "height": 1,
                    "x": 5200,
                    "y": 1800,
                    "disposition": -1,
                    "flags": {
                        "ddbActorFlags": {
                            "id": 4831017,
                            "entityTypeId": 779871897,
                            "creatureGroupId": null,
                            "creatureFlags": [],
                            "version": "999.0.0",
                            "isLegacy": false,
                            "flatAC": false,
                            "name": "Bullywug Warrior"
                        }
                    },
                    "actorLink": false,
                    "bar1": {
                        "attribute": "attributes.hp"
                    },
                    "elevation": 0,
                    "hidden": true,
                    "actorData": {
                        "_id": "eE2ESlyjy6VTBlIX",
                        "system": {},
                        "flags": {}
                    },
                    "light": {
                        "negative": false,
                        "priority": 0,
                        "alpha": 0.5,
                        "angle": 360,
                        "bright": 0,
                        "color": null,
                        "coloration": 1,
                        "dim": 0,
                        "attenuation": 0.5,
                        "luminosity": 0.5,
                        "saturation": 0,
                        "contrast": 0,
                        "shadows": 0,
                        "animation": {
                            "type": null,
                            "speed": 5,
                            "intensity": 5,
                            "reverse": false
                        },
                        "darkness": {
                            "min": 0,
                            "max": 1
                        }
                    }
                },
                {
                    "_id": "I37CD4JMZeQpEeZD",
                    "name": "Bullywug Warrior",
                    "width": 1,
                    "height": 1,
                    "x": 5200,
                    "y": 1900,
                    "disposition": -1,
                    "flags": {
                        "ddbActorFlags": {
                            "id": 4831017,
                            "entityTypeId": 779871897,
                            "creatureGroupId": null,
                            "creatureFlags": [],
                            "version": "999.0.0",
                            "isLegacy": false,
                            "flatAC": false,
                            "name": "Bullywug Warrior"
                        }
                    },
                    "actorLink": false,
                    "bar1": {
                        "attribute": "attributes.hp"
                    },
                    "elevation": 0,
                    "hidden": true,
                    "actorData": {
                        "_id": "eE2ESlyjy6VTBlIX",
                        "system": {},
                        "flags": {}
                    },
                    "light": {
                        "negative": false,
                        "priority": 0,
                        "alpha": 0.5,
                        "angle": 360,
                        "bright": 0,
                        "color": null,
                        "coloration": 1,
                        "dim": 0,
                        "attenuation": 0.5,
                        "luminosity": 0.5,
                        "saturation": 0,
                        "contrast": 0,
                        "shadows": 0,
                        "animation": {
                            "type": null,
                            "speed": 5,
                            "intensity": 5,
                            "reverse": false
                        },
                        "darkness": {
                            "min": 0,
                            "max": 1
                        }
                    }
                },
                {
                    "_id": "DZADnLvBsvsO0Noq",
                    "name": "Uni",
                    "width": 2,
                    "height": 2,
                    "x": 4800,
                    "y": 1800,
                    "disposition": -1,
                    "flags": {
                        "ddbActorFlags": {
                            "id": 4775848,
                            "entityTypeId": 779871897,
                            "creatureGroupId": null,
                            "creatureFlags": [],
                            "version": "999.0.0",
                            "isLegacy": false,
                            "flatAC": false,
                            "name": "Warhorse"
                        }
                    },
                    "actorLink": false,
                    "bar1": {
                        "attribute": "attributes.hp"
                    },
                    "elevation": 0,
                    "hidden": true,
                    "actorData": {
                        "_id": "DZADnLvBsvsO0Noq",
                        "name": "Uni",
                        "system": {},
                        "flags": {}
                    },
                    "light": {
                        "negative": false,
                        "priority": 0,
                        "alpha": 0.5,
                        "angle": 360,
                        "bright": 0,
                        "color": null,
                        "coloration": 1,
                        "dim": 0,
                        "attenuation": 0.5,
                        "luminosity": 0.5,
                        "saturation": 0,
                        "contrast": 0,
                        "shadows": 0,
                        "animation": {
                            "type": null,
                            "speed": 5,
                            "intensity": 5,
                            "reverse": false
                        },
                        "darkness": {
                            "min": 0,
                            "max": 1
                        }
                    }
                }
            ],
            "originalLink": "ddb://image/uhlh/map-0.01-woodland-pool-player.jpg",
            "foundryVersion": "12.331",
            "versions": {
                "ddbMetaData": {
                    "name": "Map 1.1: Woodland Pool View Without Tokens",
                    "bookCode": "uhlh",
                    "contentChunkId": "Map11WoodlandPool-player",
                    "lastUpdate": "1.1.6",
                    "notes": "1.1.6",
                    "tokens": "1.1.6",
                    "walls": "1.1.6",
                    "lights": "1.1.6",
                    "drawings": "1.1.6",
                    "regions": "1.1.6",
                    "foundry": "12.331"
                }
            }
        },
        "stairways": [],
        "perfect-vision": {},
        "dynamic-illumination": {},
        "ddbimporter": {
            "version": "999.0.0"
        }
    },
    "globalLight": true,
    "globalLightThreshold": 0.55,
    "grid": {
        "type": 1,
        "size": 100,
        "sizeX": 100,
        "sizeY": 100,
        "distance": 5,
        "units": "ft",
        "style": "solidLines",
        "thickness": 1,
        "color": "#000000",
        "alpha": 0.2,
        "diagonals": 0
    },
    "height": 2532,
    "initial": {
        "x": null,
        "y": null,
        "scale": 0.5
    },
    "lights": [],
    "name": "Map 1.1: Woodland Pool View Without Tokens",
    "navName": "Woodland Pool View Without Tokens",
    "padding": 0.25,
    "tokenVision": true,
    "walls": [
        {
            "dir": 0,
            "door": 0,
            "ds": 0,
            "light": 20,
            "sight": 20,
            "sound": 20,
            "move": 20,
            "c": [
                1654,
                779,
                7546,
                779
            ],
            "threshold": {
                "light": null,
                "sight": null,
                "sound": null,
                "attenuation": false
            },
            "flags": {}
        },
        {
            "dir": 0,
            "door": 0,
            "ds": 0,
            "light": 20,
            "sight": 20,
            "sound": 20,
            "move": 20,
            "c": [
                7546,
                779,
                7546,
                3184
            ],
            "threshold": {
                "light": null,
                "sight": null,
                "sound": null,
                "attenuation": false
            },
            "flags": {}
        },
        {
            "dir": 0,
            "door": 0,
            "ds": 0,
            "light": 20,
            "sight": 20,
            "sound": 20,
            "move": 20,
            "c": [
                7546,
                3184,
                1654,
                3184
            ],
            "threshold": {
                "light": null,
                "sight": null,
                "sound": null,
                "attenuation": false
            },
            "flags": {}
        },
        {
            "dir": 0,
            "door": 0,
            "ds": 0,
            "light": 20,
            "sight": 20,
            "sound": 20,
            "move": 20,
            "c": [
                1654,
                3184,
                1654,
                779
            ],
            "threshold": {
                "light": null,
                "sight": null,
                "sound": null,
                "attenuation": false
            },
            "flags": {}
        },
        {
            "dir": 0,
            "door": 0,
            "ds": 0,
            "light": 20,
            "sight": 20,
            "sound": 20,
            "move": 20,
            "c": [
                3954,
                804,
                5284,
                804
            ],
            "threshold": {
                "light": null,
                "sight": null,
                "sound": null,
                "attenuation": false
            },
            "flags": {}
        },
        {
            "dir": 0,
            "door": 0,
            "ds": 0,
            "light": 20,
            "sight": 20,
            "sound": 20,
            "move": 20,
            "c": [
                5284,
                804,
                5284,
                1034
            ],
            "threshold": {
                "light": null,
                "sight": null,
                "sound": null,
                "attenuation": false
            },
            "flags": {}
        },
        {
            "dir": 0,
            "door": 0,
            "ds": 0,
            "light": 10,
            "sight": 10,
            "sound": 10,
            "move": 0,
            "c": [
                5284,
                1034,
                3954,
                1034
            ],
            "threshold": {
                "light": null,
                "sight": null,
                "sound": null,
                "attenuation": false
            },
            "flags": {}
        },
        {
            "dir": 0,
            "door": 0,
            "ds": 0,
            "light": 10,
            "sight": 10,
            "sound": 10,
            "move": 0,
            "c": [
                3954,
                1034,
                3954,
                804
            ],
            "threshold": {
                "light": null,
                "sight": null,
                "sound": null,
                "attenuation": false
            },
            "flags": {}
        },
        {
            "light": 10,
            "sight": 10,
            "sound": 10,
            "move": 0,
            "c": [
                3200,
                750,
                3000,
                1325
            ],
            "dir": 0,
            "door": 0,
            "ds": 0,
            "threshold": {
                "light": null,
                "sight": null,
                "sound": null,
                "attenuation": false
            },
            "flags": {}
        },
        {
            "light": 10,
            "sight": 10,
            "sound": 10,
            "move": 0,
            "c": [
                3000,
                1325,
                2988,
                1513
            ],
            "dir": 0,
            "door": 0,
            "ds": 0,
            "threshold": {
                "light": null,
                "sight": null,
                "sound": null,
                "attenuation": false
            },
            "flags": {}
        },
        {
            "light": 10,
            "sight": 10,
            "sound": 10,
            "move": 0,
            "c": [
                2988,
                1513,
                3063,
                1638
            ],
            "dir": 0,
            "door": 0,
            "ds": 0,
            "threshold": {
                "light": null,
                "sight": null,
                "sound": null,
                "attenuation": false
            },
            "flags": {}
        },
        {
            "light": 10,
            "sight": 10,
            "sound": 10,
            "move": 0,
            "c": [
                3063,
                1638,
                3213,
                1788
            ],
            "dir": 0,
            "door": 0,
            "ds": 0,
            "threshold": {
                "light": null,
                "sight": null,
                "sound": null,
                "attenuation": false
            },
            "flags": {}
        },
        {
            "light": 10,
            "sight": 10,
            "sound": 10,
            "move": 0,
            "c": [
                3213,
                1788,
                3225,
                1963
            ],
            "dir": 0,
            "door": 0,
            "ds": 0,
            "threshold": {
                "light": null,
                "sight": null,
                "sound": null,
                "attenuation": false
            },
            "flags": {}
        },
        {
            "light": 10,
            "sight": 10,
            "sound": 10,
            "move": 0,
            "c": [
                3225,
                1963,
                3338,
                2188
            ],
            "dir": 0,
            "door": 0,
            "ds": 0,
            "threshold": {
                "light": null,
                "sight": null,
                "sound": null,
                "attenuation": false
            },
            "flags": {}
        },
        {
            "light": 10,
            "sight": 10,
            "sound": 10,
            "move": 0,
            "c": [
                3338,
                2188,
                3238,
                2425
            ],
            "dir": 0,
            "door": 0,
            "ds": 0,
            "threshold": {
                "light": null,
                "sight": null,
                "sound": null,
                "attenuation": false
            },
            "flags": {}
        },
        {
            "light": 10,
            "sight": 10,
            "sound": 10,
            "move": 0,
            "c": [
                3238,
                2425,
                3100,
                3225
            ],
            "dir": 0,
            "door": 0,
            "ds": 0,
            "threshold": {
                "light": null,
                "sight": null,
                "sound": null,
                "attenuation": false
            },
            "flags": {}
        },
        {
            "light": 10,
            "sight": 10,
            "sound": 10,
            "move": 0,
            "c": [
                3388,
                738,
                3538,
                3325
            ],
            "dir": 0,
            "door": 0,
            "ds": 0,
            "threshold": {
                "light": null,
                "sight": null,
                "sound": null,
                "attenuation": false
            },
            "flags": {}
        },
        {
            "light": 10,
            "sight": 10,
            "sound": 10,
            "move": 0,
            "c": [
                3613,
                888,
                3688,
                1163
            ],
            "dir": 0,
            "door": 0,
            "ds": 0,
            "threshold": {
                "light": null,
                "sight": null,
                "sound": null,
                "attenuation": false
            },
            "flags": {}
        },
        {
            "light": 10,
            "sight": 10,
            "sound": 10,
            "move": 0,
            "c": [
                3688,
                1163,
                3863,
                1113
            ],
            "dir": 0,
            "door": 0,
            "ds": 0,
            "threshold": {
                "light": null,
                "sight": null,
                "sound": null,
                "attenuation": false
            },
            "flags": {}
        },
        {
            "light": 10,
            "sight": 10,
            "sound": 10,
            "move": 0,
            "c": [
                3863,
                1113,
                4175,
                1138
            ],
            "dir": 0,
            "door": 0,
            "ds": 0,
            "threshold": {
                "light": null,
                "sight": null,
                "sound": null,
                "attenuation": false
            },
            "flags": {}
        },
        {
            "light": 10,
            "sight": 10,
            "sound": 10,
            "move": 0,
            "c": [
                4175,
                1138,
                4588,
                1138
            ],
            "dir": 0,
            "door": 0,
            "ds": 0,
            "threshold": {
                "light": null,
                "sight": null,
                "sound": null,
                "attenuation": false
            },
            "flags": {}
        },
        {
            "light": 10,
            "sight": 10,
            "sound": 10,
            "move": 0,
            "c": [
                4588,
                1138,
                4600,
                1213
            ],
            "dir": 0,
            "door": 0,
            "ds": 0,
            "threshold": {
                "light": null,
                "sight": null,
                "sound": null,
                "attenuation": false
            },
            "flags": {}
        },
        {
            "light": 10,
            "sight": 10,
            "sound": 10,
            "move": 0,
            "c": [
                4600,
                1213,
                4450,
                1300
            ],
            "dir": 0,
            "door": 0,
            "ds": 0,
            "threshold": {
                "light": null,
                "sight": null,
                "sound": null,
                "attenuation": false
            },
            "flags": {}
        },
        {
            "light": 10,
            "sight": 10,
            "sound": 10,
            "move": 0,
            "c": [
                4450,
                1300,
                4138,
                1388
            ],
            "dir": 0,
            "door": 0,
            "ds": 0,
            "threshold": {
                "light": null,
                "sight": null,
                "sound": null,
                "attenuation": false
            },
            "flags": {}
        },
        {
            "light": 10,
            "sight": 10,
            "sound": 10,
            "move": 0,
            "c": [
                4138,
                1388,
                3913,
                1500
            ],
            "dir": 0,
            "door": 0,
            "ds": 0,
            "threshold": {
                "light": null,
                "sight": null,
                "sound": null,
                "attenuation": false
            },
            "flags": {}
        },
        {
            "light": 10,
            "sight": 10,
            "sound": 10,
            "move": 0,
            "c": [
                3913,
                1500,
                3700,
                1613
            ],
            "dir": 0,
            "door": 0,
            "ds": 0,
            "threshold": {
                "light": null,
                "sight": null,
                "sound": null,
                "attenuation": false
            },
            "flags": {}
        },
        {
            "light": 10,
            "sight": 10,
            "sound": 10,
            "move": 0,
            "c": [
                3713,
                1988,
                3738,
                2250
            ],
            "dir": 0,
            "door": 0,
            "ds": 0,
            "threshold": {
                "light": null,
                "sight": null,
                "sound": null,
                "attenuation": false
            },
            "flags": {}
        },
        {
            "light": 10,
            "sight": 10,
            "sound": 10,
            "move": 0,
            "c": [
                3738,
                2250,
                3830,
                2845
            ],
            "dir": 0,
            "door": 0,
            "ds": 0,
            "threshold": {
                "light": null,
                "sight": null,
                "sound": null,
                "attenuation": false
            },
            "flags": {}
        },
        {
            "light": 10,
            "sight": 10,
            "sound": 10,
            "move": 0,
            "c": [
                3688,
                1163,
                3688,
                1563
            ],
            "dir": 0,
            "door": 0,
            "ds": 0,
            "threshold": {
                "light": null,
                "sight": null,
                "sound": null,
                "attenuation": false
            },
            "flags": {}
        },
        {
            "light": 10,
            "sight": 10,
            "sound": 10,
            "move": 0,
            "c": [
                3688,
                1563,
                3688,
                1850
            ],
            "dir": 0,
            "door": 0,
            "ds": 0,
            "threshold": {
                "light": null,
                "sight": null,
                "sound": null,
                "attenuation": false
            },
            "flags": {}
        },
        {
            "light": 10,
            "sight": 10,
            "sound": 10,
            "move": 0,
            "c": [
                3688,
                1850,
                3713,
                2000
            ],
            "dir": 0,
            "door": 0,
            "ds": 0,
            "threshold": {
                "light": null,
                "sight": null,
                "sound": null,
                "attenuation": false
            },
            "flags": {}
        },
        {
            "c": [
                3830,
                2845,
                4313,
                3213
            ],
            "light": 10,
            "move": 0,
            "sight": 10,
            "sound": 10,
            "dir": 0,
            "door": 0,
            "ds": 0,
            "threshold": {
                "light": null,
                "sight": null,
                "sound": null,
                "attenuation": false
            },
            "flags": {}
        }
    ],
    "weather": "",
    "width": 6014
}